zope/principalannotation/README.rst
zope/principalannotation/__init__.py
zope/principalannotation/configure.zcml
zope/principalannotation/interfaces.py
zope/principalannotation/tests.py
zope/principalannotation/utility.py
zope_principalannotation-6.0.dist-info/licenses/LICENSE.txt
zope_principalannotation-6.0.dist-info/METADATA
zope_principalannotation-6.0.dist-info/WHEEL
zope_principalannotation-6.0.dist-info/top_level.txt
zope_principalannotation-6.0.dist-info/RECORD
