Metadata-Version: 2.4
Name: zope.principalannotation
Version: 6.0
Summary: Annotations for Zope Principals
Home-page: https://github.com/zopefoundation/zope.principalannotation
Author: Zope Foundation and Contributors
Author-email: zope-dev@zope.dev
License: ZPL-2.1
Keywords: zope security principal annotation
Classifier: Development Status :: 5 - Production/Stable
Classifier: Environment :: Web Environment
Classifier: Intended Audience :: Developers
Classifier: License :: OSI Approved :: Zope Public License
Classifier: Programming Language :: Python
Classifier: Programming Language :: Python :: 3
Classifier: Programming Language :: Python :: 3.9
Classifier: Programming Language :: Python :: 3.10
Classifier: Programming Language :: Python :: 3.11
Classifier: Programming Language :: Python :: 3.12
Classifier: Programming Language :: Python :: 3.13
Classifier: Programming Language :: Python :: Implementation :: CPython
Classifier: Programming Language :: Python :: Implementation :: PyPy
Classifier: Natural Language :: English
Classifier: Operating System :: OS Independent
Classifier: Topic :: Internet :: WWW/HTTP
Classifier: Framework :: Zope :: 3
Requires-Python: >=3.9
License-File: LICENSE.txt
Requires-Dist: persistent>=4.4.2
Requires-Dist: setuptools
Requires-Dist: zope.annotation
Requires-Dist: zope.component>=4.5.0
Requires-Dist: zope.interface>=4.5.0
Requires-Dist: zope.location
Requires-Dist: zope.security
Requires-Dist: zope.site
Provides-Extra: test
Requires-Dist: zope.configuration; extra == "test"
Requires-Dist: zope.testing; extra == "test"
Requires-Dist: zope.site[test]; extra == "test"
Requires-Dist: zope.testrunner>=6.4; extra == "test"
Provides-Extra: docs
Requires-Dist: Sphinx; extra == "docs"
Requires-Dist: repoze.sphinx.autointerface; extra == "docs"
Requires-Dist: sphinx_rtd_theme; extra == "docs"
Dynamic: author
Dynamic: author-email
Dynamic: classifier
Dynamic: description
Dynamic: home-page
Dynamic: keywords
Dynamic: license
Dynamic: license-file
Dynamic: provides-extra
Dynamic: requires-dist
Dynamic: requires-python
Dynamic: summary
